{"meta":{"requestId":"s2md-REQ-6928d3ed7ce92","httpStatusCode":200},"result":{"tags":[],"deletedTags":[],"deletedTagCount":0,"subscriptionInfo":{"isPro":false,"proStats":false,"proAds":false,"proWho":false,"proTelco":false,"proTelcoAi":false,"proAIAssistantCalendar":false,"telco":null,"sNumber":null,"proChatgpt":true,"aibots":[{"banner_url":"https:\/\/gtc-chat.s3.eu-central-1.amazonaws.com\/chatbot-01%402x-min.png","photo_url":"https:\/\/isadmediakc.cdngtc.com\/chat\/chatbot_icon.png","title_translation":"ChatBot","key":"chatbot","name":"ChatBot","banner_option":"all","enabled":true,"show_news_feed":true}],"proBusPro":false,"proSecNum":false,"proPriMod":false,"hasTariff":false,"isTrialUsed":true,"storeProductId":null,"usage":{"secondNumberOutboundCall":{"limit":0,"remainingCount":0,"showOffer":true,"isColorRed":true,"showPackages":true,"localizations":{"title":"Increase limits","description":"Get Getcontact Premium now to increase your search limits even more.","btnTitle":null}},"dailySecondNumberInboundCall":{"limit":0,"remainingCount":0,"showOffer":true,"isColorRed":true,"showPackages":true,"localizations":{"title":"Increase limits","description":"Get Getcontact Premium now to increase your search limits even more.","btnTitle":null}},"secondNumberOutboundSms":{"limit":0,"remainingCount":0,"showOffer":true,"isColorRed":true,"showPackages":true,"localizations":{"title":"Increase limits","description":"Get Getcontact Premium now to increase your search limits even more.","btnTitle":null}},"dailySecondNumberInboundSms":{"limit":0,"remainingCount":0,"showOffer":true,"isColorRed":true,"showPackages":true,"localizations":{"title":"Increase limits","description":"Get Getcontact Premium now to increase your search limits even more.","btnTitle":null}},"search":{"limit":200,"remainingCount":199,"showOffer":false,"isColorRed":false,"showPackages":false,"localizations":{"title":"Increase limits","description":"Get Getcontact Premium now to increase your search limits even more.","btnTitle":"Try Premium"}},"numberDetail":{"limit":0,"remainingCount":0,"showOffer":true,"isColorRed":true,"showPackages":true,"localizations":{"title":"Increase limits","description":"Get Getcontact Premium now to increase your search limits even more.","btnTitle":"Try Premium"}},"trustScore":{"limit":0,"remainingCount":0,"showOffer":true,"isColorRed":true,"showPackages":true,"localizations":{"title":"Increase limits","description":"Get Getcontact Premium now to increase your search limits even more.","btnTitle":"Try Premium"}},"biography":{"limit":5,"remainingCount":5,"showOffer":false,"isColorRed":false,"showPackages":false,"localizations":{"title":"Increase limits","description":"Get Getcontact Premium now to increase your search limits even more.","btnTitle":"Try Premium"}}},"usageWithPackage":{"free":{"renewDate":"2025-11-30 23:59:59","list":[{"limit":200,"remainingCount":199,"showOffer":false,"isColorRed":false,"showPackages":false,"color":"#F3BD33","darkColor":"#F3BD33","type":"search"},{"limit":5,"remainingCount":5,"showOffer":false,"isColorRed":false,"showPackages":false,"color":"#36BDC6","darkColor":"#36BDC6","type":"biography"}],"tabName":"Free","typeName":"Free","localizations":{"title":"Increase limits","description":"Get Getcontact Premium now to increase your search limits even more.","btnTitle":"Try Premium"}}},"premiumType":"free","premiumTypeName":"Free","showTrustScoreUsage":false,"showTagUsage":true,"showSubscriptionInfo":true,"isMainSubscriptionMenuActive":true,"showSubscriptionPackages":true,"showStatics":false,"showWhoLookedMyProfile":true,"renewDate":"2025-11-30 23:59:59","receiptStartDate":"2025-11-01 00:00:00","receiptEndDate":"2025-11-30 00:00:00","lastPackageText":null,"subsInfoButtonText":"Try Premium","subsInfoButtonIntroText":"Get Getcontact Premium now to increase your search limits even more.","isShowOwnTagShouldPremium":false,"isDisableOwnTagCount":false},"deletedTagRequestButton":"none","verify":null,"infoBanner":false,"teaser":{"active":true},"isBlockedBySearchedUser":false,"adSettings":{"closeAdBtn":true,"showCM":false,"interstitial":{"interval":54000,"providers":[{"mediation":"applovin","smallScreenUnitId":"","unitId":"ab2311988d12ca0a","status":true,"video":true}],"locations":{"showTagsResult":true,"showTagsResultDetail":true,"manuelSearch":true,"shareSearch":true,"showTagsShare":true,"searchBack":false,"tagsDetailBack":false},"noFillInterval":10,"searchCount":100,"reducedInterval":54000,"hera":false},"native":{"searchDetail":[{"mediation":"applovin","smallScreenUnitId":"","unitId":"f56a9ca467244b7a","status":true,"video":false}],"notificationList":null,"newsFeed":[{"mediation":"applovin","smallScreenUnitId":"","unitId":"95694d09a822d8a1","status":true,"video":false}],"searchDetailTags":null,"myTags":[{"mediation":"applovin","smallScreenUnitId":"","unitId":"cb6fa594c682b74e","status":true,"video":false}],"notificationListDirect":[{"mediation":"applovin","smallScreenUnitId":"","unitId":"cb6fa594c682b74e","status":true,"video":false}],"quickContactsList":[{"mediation":"applovin","smallScreenUnitId":"","unitId":"cb6fa594c682b74e","status":true,"video":false}],"searchHistory":[{"mediation":"applovin","smallScreenUnitId":"","unitId":"cb6fa594c682b74e","status":true,"video":false}],"callHistory":[{"mediation":"applovin","smallScreenUnitId":"","unitId":"cb6fa594c682b74e","status":true,"video":false}],"callerId":null,"searchLimits":null,"settings":null,"callResult":[{"mediation":"applovin","smallScreenUnitId":"","unitId":"f6969808a69b2194","status":true,"video":false}],"searchWithGtc":null,"spamSettings":null,"removeTag":null},"adOpen":null,"rewardedAd":{"expired_at":6000,"monthly_capping":4,"tag_show_time":6000,"interval":50,"noFillInterval":60,"providers":[],"locations":{"blurryPaywall":false}}},"tagCount":0}}